Metadata-Version: 2.4
Name: llama-index-vector-stores-epsilla
Version: 0.4.1
Summary: llama-index vector_stores epsilla integration
Author-email: Your Name <you@example.com>
License-Expression: MIT
License-File: LICENSE
Requires-Python: <4.0,>=3.9
Requires-Dist: llama-index-core<0.15,>=0.13.0
Requires-Dist: pyepsilla<0.4,>=0.3.3
